panda_server_sdk/__init__.py
panda_server_sdk/panda_server_sdk.py
panda_server_sdk/panda_server_sdk_keys.py
panda_server_sdk-1.1.0.dist-info/METADATA
panda_server_sdk-1.1.0.dist-info/WHEEL
panda_server_sdk-1.1.0.dist-info/top_level.txt
panda_server_sdk-1.1.0.dist-info/RECORD
