Metadata-Version: 2.1
Name: panda-server-sdk
Version: 1.1.0
Summary: Python SDK for Panda Server
Home-page: UNKNOWN
Author: UNKNOWN
Author-email: UNKNOWN
License: UNKNOWN
Platform: UNKNOWN
